{ 
  "configurations" : [
    { 
      "name" : "0",
      "parameters" :{
        "align_del" : "align_del_dis",
        "ber_bit_err_total_cnt" : "bit_err_total_cnt_10g",
        "ber_clken" : "ber_clk_dis",
        "ber_xus_timer_window" : "21'd19530",
        "bitslip_mode" : "bitslip_en",
        "blksync_bitslip_type" : "bitslip_comb",
        "blksync_bitslip_wait_cnt" : "3'd1",
        "blksync_bitslip_wait_type" : "bitslip_cnt",
        "blksync_bypass" : "blksync_bypass_en",
        "blksync_clken" : "blksync_clk_dis",
        "blksync_enum_invalid_sh_cnt" : "enum_invalid_sh_cnt_10g",
        "blksync_knum_sh_cnt_postlock" : "knum_sh_cnt_postlock_10g",
        "blksync_knum_sh_cnt_prelock" : "knum_sh_cnt_prelock_10g",
        "blksync_pipeln" : "blksync_pipeln_dis",
        "clr_errblk_cnt_en" : "disable",
        "control_del" : "control_del_none",
        "crcchk_bypass" : "crcchk_bypass_en",
        "crcchk_clken" : "crcchk_clk_dis",
        "crcchk_inv" : "crcchk_inv_en",
        "crcchk_pipeln" : "crcchk_pipeln_en",
        "crcflag_pipeln" : "crcflag_pipeln_en",
        "ctrl_bit_reverse" : "ctrl_bit_reverse_dis",
        "data_bit_reverse" : "data_bit_reverse_dis",
        "dec_64b66b_rxsm_bypass" : "dec_64b66b_rxsm_bypass_en",
        "dec64b66b_clken" : "dec64b66b_clk_dis",
        "descrm_bypass" : "descrm_bypass_en",
        "descrm_clken" : "descrm_clk_dis",
        "descrm_mode" : "async",
        "descrm_pipeln" : "enable",
        "dft_clk_out_sel" : "rx_master_clk",
        "dis_signal_ok" : "dis_signal_ok_en",
        "dispchk_bypass" : "dispchk_bypass_en",
        "empty_flag_type" : "empty_rd_side",
        "fast_path" : "fast_path_en",
        "fec_clken" : "fec_clk_dis",
        "fec_enable" : "fec_dis",
        "fifo_double_read" : "fifo_double_read_dis",
        "fifo_stop_rd" : "n_rd_empty",
        "fifo_stop_wr" : "n_wr_full",
        "force_align" : "force_align_dis",
        "frmsync_bypass" : "frmsync_bypass_en",
        "frmsync_clken" : "frmsync_clk_dis",
        "frmsync_enum_scrm" : "enum_scrm_default",
        "frmsync_enum_sync" : "enum_sync_default",
        "frmsync_flag_type" : "location_only",
        "frmsync_knum_sync" : "knum_sync_default",
        "frmsync_mfrm_length" : "16'd2048",
        "frmsync_pipeln" : "frmsync_pipeln_en",
        "full_flag_type" : "full_wr_side",
        "gb_rx_idwidth" : "width_40",
        "gb_rx_odwidth" : "width_40",
        "gbexp_clken" : "gbexp_clk_en",
        "low_latency_en" : "disable",
        "lpbk_mode" : "lpbk_dis",
        "master_clk_sel" : "master_rx_pma_clk",
        "pempty_flag_type" : "pempty_rd_side",
        "pfull_flag_type" : "pfull_wr_side",
        "phcomp_rd_del" : "phcomp_rd_del2",
        "pld_if_type" : "fifo",
        "prot_mode" : "basic_mode",
        "rand_clken" : "rand_clk_dis",
        "rd_clk_sel" : "rd_rx_pld_clk",
        "rdfifo_clken" : "rdfifo_clk_en",
        "rx_fifo_write_ctrl" : "blklock_stops",
        "rx_scrm_width" : "bit64",
        "rx_sh_location" : "msb",
        "rx_signal_ok_sel" : "synchronized_ver",
        "rx_sm_bypass" : "rx_sm_bypass_en",
        "rx_sm_hiber" : "rx_sm_hiber_en",
        "rx_sm_pipeln" : "rx_sm_pipeln_en",
        "rx_testbus_sel" : "rx_fifo_testbus1",
        "rx_true_b2b" : "b2b",
        "rxfifo_empty" : "empty_default",
        "rxfifo_full" : "full_default",
        "rxfifo_mode" : "generic_basic",
        "rxfifo_pempty" : "5'd7",
        "rxfifo_pfull" : "5'd23",
        "stretch_num_stages" : "one_stage",
        "sup_mode" : "user_mode",
        "test_mode" : "test_off",
        "wrfifo_clken" : "wrfifo_clk_en",
        "advanced_user_mode" : "disable",
        "reconfig_settings" : "{}"
      }
    },
    { 
      "name" : "1",
      "parameters" :{
        "align_del" : "align_del_dis",
        "ber_bit_err_total_cnt" : "bit_err_total_cnt_10g",
        "ber_clken" : "ber_clk_en",
        "ber_xus_timer_window" : "21'd19530",
        "bitslip_mode" : "bitslip_dis",
        "blksync_bitslip_type" : "bitslip_comb",
        "blksync_bitslip_wait_cnt" : "3'd1",
        "blksync_bitslip_wait_type" : "bitslip_cnt",
        "blksync_bypass" : "blksync_bypass_dis",
        "blksync_clken" : "blksync_clk_en",
        "blksync_enum_invalid_sh_cnt" : "enum_invalid_sh_cnt_10g",
        "blksync_knum_sh_cnt_postlock" : "knum_sh_cnt_postlock_10g",
        "blksync_knum_sh_cnt_prelock" : "knum_sh_cnt_prelock_10g",
        "blksync_pipeln" : "blksync_pipeln_dis",
        "clr_errblk_cnt_en" : "enable",
        "control_del" : "control_del_none",
        "crcchk_bypass" : "crcchk_bypass_en",
        "crcchk_clken" : "crcchk_clk_dis",
        "crcchk_inv" : "crcchk_inv_en",
        "crcchk_pipeln" : "crcchk_pipeln_en",
        "crcflag_pipeln" : "crcflag_pipeln_en",
        "ctrl_bit_reverse" : "ctrl_bit_reverse_en",
        "data_bit_reverse" : "data_bit_reverse_dis",
        "dec_64b66b_rxsm_bypass" : "dec_64b66b_rxsm_bypass_dis",
        "dec64b66b_clken" : "dec64b66b_clk_en",
        "descrm_bypass" : "descrm_bypass_dis",
        "descrm_clken" : "descrm_clk_en",
        "descrm_mode" : "async",
        "descrm_pipeln" : "enable",
        "dft_clk_out_sel" : "rx_master_clk",
        "dis_signal_ok" : "dis_signal_ok_en",
        "dispchk_bypass" : "dispchk_bypass_en",
        "empty_flag_type" : "empty_rd_side",
        "fast_path" : "fast_path_dis",
        "fec_clken" : "fec_clk_dis",
        "fec_enable" : "fec_dis",
        "fifo_double_read" : "fifo_double_read_dis",
        "fifo_stop_rd" : "n_rd_empty",
        "fifo_stop_wr" : "n_wr_full",
        "force_align" : "force_align_dis",
        "frmsync_bypass" : "frmsync_bypass_en",
        "frmsync_clken" : "frmsync_clk_dis",
        "frmsync_enum_scrm" : "enum_scrm_default",
        "frmsync_enum_sync" : "enum_sync_default",
        "frmsync_flag_type" : "location_only",
        "frmsync_knum_sync" : "knum_sync_default",
        "frmsync_mfrm_length" : "16'd2048",
        "frmsync_pipeln" : "frmsync_pipeln_en",
        "full_flag_type" : "full_wr_side",
        "gb_rx_idwidth" : "width_32",
        "gb_rx_odwidth" : "width_66",
        "gbexp_clken" : "gbexp_clk_en",
        "low_latency_en" : "disable",
        "lpbk_mode" : "lpbk_dis",
        "master_clk_sel" : "master_rx_pma_clk",
        "pempty_flag_type" : "pempty_rd_side",
        "pfull_flag_type" : "pfull_wr_side",
        "phcomp_rd_del" : "phcomp_rd_del2",
        "pld_if_type" : "fifo",
        "prot_mode" : "teng_baser_mode",
        "rand_clken" : "rand_clk_en",
        "rd_clk_sel" : "rd_rx_pld_clk",
        "rdfifo_clken" : "rdfifo_clk_en",
        "rx_fifo_write_ctrl" : "blklock_stops",
        "rx_scrm_width" : "bit64",
        "rx_sh_location" : "lsb",
        "rx_signal_ok_sel" : "synchronized_ver",
        "rx_sm_bypass" : "rx_sm_bypass_dis",
        "rx_sm_hiber" : "rx_sm_hiber_en",
        "rx_sm_pipeln" : "rx_sm_pipeln_en",
        "rx_testbus_sel" : "rx_fifo_testbus1",
        "rx_true_b2b" : "b2b",
        "rxfifo_empty" : "empty_default",
        "rxfifo_full" : "full_default",
        "rxfifo_mode" : "clk_comp_10g",
        "rxfifo_pempty" : "5'd2",
        "rxfifo_pfull" : "5'd23",
        "stretch_num_stages" : "two_stage",
        "sup_mode" : "user_mode",
        "test_mode" : "test_off",
        "wrfifo_clken" : "wrfifo_clk_en",
        "advanced_user_mode" : "disable",
        "reconfig_settings" : "{}"
      }
    },
    { 
      "name" : "2",
      "parameters" :{
        "align_del" : "align_del_dis",
        "ber_bit_err_total_cnt" : "bit_err_total_cnt_10g",
        "ber_clken" : "ber_clk_dis",
        "ber_xus_timer_window" : "21'd19530",
        "bitslip_mode" : "bitslip_en",
        "blksync_bitslip_type" : "bitslip_comb",
        "blksync_bitslip_wait_cnt" : "3'd1",
        "blksync_bitslip_wait_type" : "bitslip_cnt",
        "blksync_bypass" : "blksync_bypass_en",
        "blksync_clken" : "blksync_clk_dis",
        "blksync_enum_invalid_sh_cnt" : "enum_invalid_sh_cnt_10g",
        "blksync_knum_sh_cnt_postlock" : "knum_sh_cnt_postlock_10g",
        "blksync_knum_sh_cnt_prelock" : "knum_sh_cnt_prelock_10g",
        "blksync_pipeln" : "blksync_pipeln_dis",
        "clr_errblk_cnt_en" : "disable",
        "control_del" : "control_del_none",
        "crcchk_bypass" : "crcchk_bypass_en",
        "crcchk_clken" : "crcchk_clk_dis",
        "crcchk_inv" : "crcchk_inv_en",
        "crcchk_pipeln" : "crcchk_pipeln_en",
        "crcflag_pipeln" : "crcflag_pipeln_en",
        "ctrl_bit_reverse" : "ctrl_bit_reverse_dis",
        "data_bit_reverse" : "data_bit_reverse_dis",
        "dec_64b66b_rxsm_bypass" : "dec_64b66b_rxsm_bypass_en",
        "dec64b66b_clken" : "dec64b66b_clk_dis",
        "descrm_bypass" : "descrm_bypass_en",
        "descrm_clken" : "descrm_clk_dis",
        "descrm_mode" : "async",
        "descrm_pipeln" : "enable",
        "dft_clk_out_sel" : "rx_master_clk",
        "dis_signal_ok" : "dis_signal_ok_en",
        "dispchk_bypass" : "dispchk_bypass_en",
        "empty_flag_type" : "empty_rd_side",
        "fast_path" : "fast_path_en",
        "fec_clken" : "fec_clk_dis",
        "fec_enable" : "fec_dis",
        "fifo_double_read" : "fifo_double_read_dis",
        "fifo_stop_rd" : "n_rd_empty",
        "fifo_stop_wr" : "n_wr_full",
        "force_align" : "force_align_dis",
        "frmsync_bypass" : "frmsync_bypass_en",
        "frmsync_clken" : "frmsync_clk_dis",
        "frmsync_enum_scrm" : "enum_scrm_default",
        "frmsync_enum_sync" : "enum_sync_default",
        "frmsync_flag_type" : "location_only",
        "frmsync_knum_sync" : "knum_sync_default",
        "frmsync_mfrm_length" : "16'd2048",
        "frmsync_pipeln" : "frmsync_pipeln_en",
        "full_flag_type" : "full_wr_side",
        "gb_rx_idwidth" : "width_40",
        "gb_rx_odwidth" : "width_40",
        "gbexp_clken" : "gbexp_clk_en",
        "low_latency_en" : "disable",
        "lpbk_mode" : "lpbk_dis",
        "master_clk_sel" : "master_rx_pma_clk",
        "pempty_flag_type" : "pempty_rd_side",
        "pfull_flag_type" : "pfull_wr_side",
        "phcomp_rd_del" : "phcomp_rd_del2",
        "pld_if_type" : "fifo",
        "prot_mode" : "basic_mode",
        "rand_clken" : "rand_clk_dis",
        "rd_clk_sel" : "rd_rx_pld_clk",
        "rdfifo_clken" : "rdfifo_clk_en",
        "rx_fifo_write_ctrl" : "blklock_stops",
        "rx_scrm_width" : "bit64",
        "rx_sh_location" : "msb",
        "rx_signal_ok_sel" : "synchronized_ver",
        "rx_sm_bypass" : "rx_sm_bypass_en",
        "rx_sm_hiber" : "rx_sm_hiber_en",
        "rx_sm_pipeln" : "rx_sm_pipeln_en",
        "rx_testbus_sel" : "rx_fifo_testbus1",
        "rx_true_b2b" : "b2b",
        "rxfifo_empty" : "empty_default",
        "rxfifo_full" : "full_default",
        "rxfifo_mode" : "generic_basic",
        "rxfifo_pempty" : "5'd7",
        "rxfifo_pfull" : "5'd23",
        "stretch_num_stages" : "one_stage",
        "sup_mode" : "user_mode",
        "test_mode" : "test_off",
        "wrfifo_clken" : "wrfifo_clk_en",
        "advanced_user_mode" : "disable",
        "reconfig_settings" : "{}"
      }
    }
  ]
}

