{ 
  "configurations" : [
    { 
      "name" : "0",
      "parameters" :{
        "hd_chnl_hip_en" : "enable",
        "hd_chnl_transparent_pcs_rx" : "disable",
        "hd_chnl_hrdrstctl_en" : "enable",
        "hd_chnl_prot_mode_rx" : "pcie_g3_capable_rx",
        "hd_chnl_ctrl_plane_bonding_rx" : "ctrl_master_rx",
        "hd_chnl_pma_dw_rx" : "pcie_g3_dyn_dw_rx",
        "hd_chnl_pld_fifo_mode_rx" : "reg_rx",
        "hd_chnl_shared_fifo_width_rx" : "single_rx",
        "hd_chnl_low_latency_en_rx" : "disable",
        "hd_chnl_func_mode" : "enable",
        "hd_chnl_channel_operation_mode" : "tx_rx_pair_enabled",
        "hd_chnl_lpbk_en" : "disable",
        "hd_10g_advanced_user_mode_rx" : "disable",
        "hd_chnl_frequency_rules_en" : "enable",
        "hd_chnl_pma_rx_clk_hz" : "30'd500000000",
        "hd_chnl_pld_rx_clk_hz" : "30'd0",
        "hd_chnl_fref_clk_hz" : "30'd125000000",
        "hd_chnl_clklow_clk_hz" : "30'd125000000",
        "hd_fifo_channel_operation_mode" : "tx_rx_pair_enabled",
        "hd_fifo_prot_mode_rx" : "non_teng_mode_rx",
        "hd_fifo_shared_fifo_width_rx" : "single_rx",
        "hd_10g_channel_operation_mode" : "tx_rx_pair_enabled",
        "hd_10g_lpbk_en" : "disable",
        "hd_10g_pma_dw_rx" : "pma_64b_rx",
        "hd_10g_fifo_mode_rx" : "fifo_rx",
        "hd_10g_prot_mode_rx" : "disabled_prot_mode_rx",
        "hd_10g_low_latency_en_rx" : "disable",
        "hd_10g_shared_fifo_width_rx" : "single_rx",
        "hd_10g_test_bus_mode" : "rx",
        "hd_8g_channel_operation_mode" : "tx_rx_pair_enabled",
        "hd_8g_lpbk_en" : "disable",
        "hd_8g_prot_mode_rx" : "pipe_g3_rx",
        "hd_8g_hip_mode" : "enable",
        "hd_8g_pma_dw_rx" : "pma_10b_rx",
        "hd_8g_fifo_mode_rx" : "reg_rx",
        "hd_g3_prot_mode" : "pipe_g3",
        "hd_krfec_channel_operation_mode" : "tx_rx_pair_enabled",
        "hd_krfec_lpbk_en" : "disable",
        "hd_krfec_prot_mode_rx" : "disabled_prot_mode_rx",
        "hd_krfec_low_latency_en_rx" : "disable",
        "hd_krfec_test_bus_mode" : "tx",
        "hd_pmaif_lpbk_en" : "disable",
        "hd_pmaif_channel_operation_mode" : "tx_rx_pair_enabled",
        "hd_pmaif_sim_mode" : "disable",
        "hd_pmaif_prot_mode_rx" : "eightg_g3_pcie_g3_hip_mode_rx",
        "hd_pmaif_pma_dw_rx" : "pcie_g3_dyn_dw_rx",
        "hd_pldif_prot_mode_rx" : "eightg_and_g3_reg_mode_hip_rx",
        "hd_pldif_hrdrstctl_en" : "enable",
        "pcs_rx_block_sel" : "eightg",
        "pcs_rx_clk_sel" : "pcs_rx_clk",
        "pcs_rx_hip_clk_en" : "hip_rx_enable",
        "pcs_rx_output_sel" : "teng_output",
        "pcs_rx_clk_out_sel" : "eightg_clk_out",
        "reconfig_settings" : "{}"
      }
    },
    { 
      "name" : "1",
      "parameters" :{
        "hd_chnl_hip_en" : "disable",
        "hd_chnl_transparent_pcs_rx" : "disable",
        "hd_chnl_hrdrstctl_en" : "disable",
        "hd_chnl_prot_mode_rx" : "basic_8gpcs_rm_enable_rx",
        "hd_chnl_ctrl_plane_bonding_rx" : "individual_rx",
        "hd_chnl_pma_dw_rx" : "pma_10b_rx",
        "hd_chnl_pld_fifo_mode_rx" : "reg_rx",
        "hd_chnl_shared_fifo_width_rx" : "single_rx",
        "hd_chnl_low_latency_en_rx" : "disable",
        "hd_chnl_func_mode" : "enable",
        "hd_chnl_channel_operation_mode" : "tx_rx_pair_enabled",
        "hd_chnl_lpbk_en" : "disable",
        "hd_10g_advanced_user_mode_rx" : "disable",
        "hd_chnl_frequency_rules_en" : "enable",
        "hd_chnl_pma_rx_clk_hz" : "30'd500000000",
        "hd_chnl_pld_rx_clk_hz" : "30'd0",
        "hd_chnl_fref_clk_hz" : "30'd125000000",
        "hd_chnl_clklow_clk_hz" : "30'd125000000",
        "hd_fifo_channel_operation_mode" : "tx_rx_pair_enabled",
        "hd_fifo_prot_mode_rx" : "non_teng_mode_rx",
        "hd_fifo_shared_fifo_width_rx" : "single_rx",
        "hd_10g_channel_operation_mode" : "tx_rx_pair_enabled",
        "hd_10g_lpbk_en" : "disable",
        "hd_10g_pma_dw_rx" : "pma_64b_rx",
        "hd_10g_fifo_mode_rx" : "fifo_rx",
        "hd_10g_prot_mode_rx" : "disabled_prot_mode_rx",
        "hd_10g_low_latency_en_rx" : "disable",
        "hd_10g_shared_fifo_width_rx" : "single_rx",
        "hd_10g_test_bus_mode" : "rx",
        "hd_8g_channel_operation_mode" : "tx_rx_pair_enabled",
        "hd_8g_lpbk_en" : "disable",
        "hd_8g_prot_mode_rx" : "basic_rm_enable_rx",
        "hd_8g_hip_mode" : "disable",
        "hd_8g_pma_dw_rx" : "pma_10b_rx",
        "hd_8g_fifo_mode_rx" : "reg_rx",
        "hd_g3_prot_mode" : "disabled_prot_mode",
        "hd_krfec_channel_operation_mode" : "tx_rx_pair_enabled",
        "hd_krfec_lpbk_en" : "disable",
        "hd_krfec_prot_mode_rx" : "disabled_prot_mode_rx",
        "hd_krfec_low_latency_en_rx" : "disable",
        "hd_krfec_test_bus_mode" : "tx",
        "hd_pmaif_lpbk_en" : "disable",
        "hd_pmaif_channel_operation_mode" : "tx_rx_pair_enabled",
        "hd_pmaif_sim_mode" : "disable",
        "hd_pmaif_prot_mode_rx" : "eightg_basic_mode_rx",
        "hd_pmaif_pma_dw_rx" : "pma_10b_rx",
        "hd_pldif_prot_mode_rx" : "eightg_and_g3_reg_mode_rx",
        "hd_pldif_hrdrstctl_en" : "disable",
        "pcs_rx_block_sel" : "eightg",
        "pcs_rx_clk_sel" : "pcs_rx_clk",
        "pcs_rx_hip_clk_en" : "hip_rx_disable",
        "pcs_rx_output_sel" : "teng_output",
        "pcs_rx_clk_out_sel" : "eightg_clk_out",
        "reconfig_settings" : "{}"
      }
    }
  ]
}

